Metadata-Version: 2.1
Name: ftw.noticeboard
Version: 1.1.3
Summary: ftw.noticeboard
Home-page: https://github.com/4teamwork/ftw.noticeboard
Author: 4teamwork AG
Author-email: mailto:info@4teamwork.ch
License: GPL2
Keywords: ftw noticeboard
Platform: UNKNOWN
Classifier: Framework :: Plone
Classifier: Framework :: Plone :: 4.3
Classifier: License :: OSI Approved :: GNU General Public License (GPL)
Classifier: Programming Language :: Python
Classifier: Programming Language :: Python :: 2.7
Classifier: Topic :: Software Development :: Libraries :: Python Modules
Provides-Extra: tests
